.clang-format
.flake8
.gitignore
.gitmodules
CHANGELOG.md
CODEOWNERS
CODE_OF_CONDUCT
Dockerfile
Dockerfile-cuda
Dockerfile-embedded
LICENSE
MANIFEST.in
Makefile
README.md
__init__.py
description.txt
packages.txt
setup.py
./src/opendr/__init__.py
./src/opendr/_setup.py
./src/opendr/_version.py
./src/opendr/control/__init__.py
./src/opendr/engine/__init__.py
./src/opendr/engine/constants.py
./src/opendr/engine/data.py
./src/opendr/engine/datasets.py
./src/opendr/engine/example_learner.py
./src/opendr/engine/learners.py
./src/opendr/engine/target.py
./src/opendr/perception/__init__.py
./src/opendr/perception/face_recognition/__init__.py
./src/opendr/perception/face_recognition/dependencies.ini
./src/opendr/perception/face_recognition/face_recognition_learner.py
./src/opendr/perception/face_recognition/algorithm/README.md
./src/opendr/perception/face_recognition/algorithm/__init__.py
./src/opendr/perception/face_recognition/algorithm/align/__init__.py
./src/opendr/perception/face_recognition/algorithm/align/align.py
./src/opendr/perception/face_recognition/algorithm/align/align_trans.py
./src/opendr/perception/face_recognition/algorithm/align/box_utils.py
./src/opendr/perception/face_recognition/algorithm/align/detector.py
./src/opendr/perception/face_recognition/algorithm/align/first_stage.py
./src/opendr/perception/face_recognition/algorithm/align/get_nets.py
./src/opendr/perception/face_recognition/algorithm/align/matlab_cp2tform.py
./src/opendr/perception/face_recognition/algorithm/align/onet.npy
./src/opendr/perception/face_recognition/algorithm/align/pnet.npy
./src/opendr/perception/face_recognition/algorithm/align/rnet.npy
./src/opendr/perception/face_recognition/algorithm/backbone/__init__.py
./src/opendr/perception/face_recognition/algorithm/backbone/model_irse.py
./src/opendr/perception/face_recognition/algorithm/backbone/model_mobilenet.py
./src/opendr/perception/face_recognition/algorithm/backbone/model_resnet.py
./src/opendr_toolkit_face_recognition.egg-info/PKG-INFO
./src/opendr_toolkit_face_recognition.egg-info/SOURCES.txt
./src/opendr_toolkit_face_recognition.egg-info/dependency_links.txt
./src/opendr_toolkit_face_recognition.egg-info/requires.txt
./src/opendr_toolkit_face_recognition.egg-info/top_level.txt
